swisslandstats/__init__.py
swisslandstats/dataframe.py
swisslandstats/geometry.py
swisslandstats/plotting.py
swisslandstats/settings.py
swisslandstats/utils.py
swisslandstats_geopy-0.12.0.dist-info/LICENSE.txt
swisslandstats_geopy-0.12.0.dist-info/METADATA
swisslandstats_geopy-0.12.0.dist-info/WHEEL
swisslandstats_geopy-0.12.0.dist-info/top_level.txt
swisslandstats_geopy-0.12.0.dist-info/RECORD
