Metadata-Version: 2.2
Name: swisslandstats-geopy
Version: 0.12.0
Summary: Python for the Swiss Federal Statistics Geodata
Author-email: Martí Bosch <marti.bosch@epfl.ch>
License: GPL-3.0
Project-URL: Repository, https://github.com/martibosch/swisslandstats-geopy
Classifier: License :: OSI Approved :: GNU General Public License v3 (GPLv3)
Classifier: Natural Language :: English
Classifier: Programming Language :: Python :: 3
Classifier: Programming Language :: Python :: 3.9
Classifier: Programming Language :: Python :: 3.10
Classifier: Programming Language :: Python :: 3.11
Classifier: Programming Language :: Python :: 3.12
Classifier: Programming Language :: Python :: 3.13
Requires-Python: >=3.9
License-File: LICENSE.txt
Requires-Dist: matplotlib>=2.2.0
Requires-Dist: numpy>=1.15.0
Requires-Dist: pandas>=0.17.0
Requires-Dist: pooch>=1.0.0
Requires-Dist: rasterio>=1.0.0
Requires-Dist: xarray
Provides-Extra: geo
Requires-Dist: geopandas>=0.10.0; extra == "geo"
Requires-Dist: osmnx>=1.0.0; extra == "geo"
Provides-Extra: test
Requires-Dist: coverage[toml]; extra == "test"
Requires-Dist: pytest; extra == "test"
Requires-Dist: pytest-cov; extra == "test"
Requires-Dist: responses; extra == "test"
Requires-Dist: ruff; extra == "test"
Provides-Extra: dev
Requires-Dist: build; extra == "dev"
Requires-Dist: commitizen; extra == "dev"
Requires-Dist: pre-commit; extra == "dev"
Requires-Dist: pip; extra == "dev"
Requires-Dist: toml; extra == "dev"
Requires-Dist: tox; extra == "dev"
Requires-Dist: tox-uv; extra == "dev"
Requires-Dist: twine; extra == "dev"
Provides-Extra: doc
Requires-Dist: m2r2; extra == "doc"
Requires-Dist: pydata-sphinx-theme; extra == "doc"
Requires-Dist: sphinx; extra == "doc"
